binary_to_seven_segement_display_converter/binary_to_sevensegment.v
 module binary_to_sevensegment(bin,a,b,c,d,e,f,g );
 input[3:0]bin;
 output reg a,b,c,d,e,f,g;
  always @(*) 
  begin
  case(bin)
            4'b0000: {a,b,c,d,e,f,g} = 7'b1111110;
            4'b0001: {a,b,c,d,e,f,g} = 7'b0110000;
            4'b0010: {a,b,c,d,e,f,g} = 7'b1101101;
            4'b0011: {a,b,c,d,e,f,g} = 7'b1111001;
            4'b0100: {a,b,c,d,e,f,g} = 7'b0110011;
            4'b0101: {a,b,c,d,e,f,g} = 7'b1011011;
            4'b0110: {a,b,c,d,e,f,g} = 7'b1011111;
            4'b0111: {a,b,c,d,e,f,g} = 7'b1110000;
            4'b1000: {a,b,c,d,e,f,g} = 7'b1111111;
            4'b1001: {a,b,c,d,e,f,g} = 7'b1111011;
            default: {a,b,c,d,e,f,g} = 7'b0000000;
        endcase
    end
 endmodule

binary_to_seven_segement_display_converter/binary_to_sevensegment_tb.v
`include "binary_to_sevensegment.v"
module binary_to_sevensegment_tb();
 reg[3:0]bin;
 wire a,b,c,d,e,f,g;
 binary_to_sevensegment uut(bin,a,b,c,d,e,f,g);
 initial
 begin
    $dumpfile("binary_to_sevensegment.vcd");
    $dumpvars(0,binary_to_sevensegment_tb);
 bin=4'b0000; #10
 bin=4'b0001; #10
 bin=4'b0010; #10
 bin=4'b0011; #10
 bin=4'b0100; #10
 bin=4'b0101; #10
 bin=4'b0110; #10
 bin=4'b0111; #10
 bin=4'b1000; #10
 bin=4'b1001; #10
 bin=4'b1010; #10
 
 $finish;
 end
 endmodule

binary_to_seven_segement_display_converter/binary_to_sevensegment.vcd
$date
	Fri Jun 13 00:52:16 2025
$end
$version
	Icarus Verilog
$end
$timescale
	1s
$end
$scope module binary_to_sevensegment_tb $end
$var wire 1 ! g $end
$var wire 1 " f $end
$var wire 1 # e $end
$var wire 1 $ d $end
$var wire 1 % c $end
$var wire 1 & b $end
$var wire 1 ' a $end
$var reg 4 ( bin [3:0] $end
$scope module uut $end
$var wire 4 ) bin [3:0] $end
$var reg 1 ' a $end
$var reg 1 & b $end
$var reg 1 % c $end
$var reg 1 $ d $end
$var reg 1 # e $end
$var reg 1 " f $end
$var reg 1 ! g $end
$upscope $end
$upscope $end
$enddefinitions $end
$comment Show the parameter values. $end
$dumpall
$end
#0
$dumpvars
b0 )
b0 (
1'
1&
1%
1$
1#
1"
0!
$end
#10
0'
0$
0#
0"
b1 (
b1 )
#20
1'
0%
1$
1#
1!
b10 (
b10 )
#30
1%
0#
b11 (
b11 )
#40
0'
0$
1"
b100 (
b100 )
#50
1'
0&
1$
b101 (
b101 )
#60
1#
b110 (
b110 )
#70
1&
0$
0#
0"
0!
b111 (
b111 )
#80
1$
1#
1"
1!
b1000 (
b1000 )
#90
0#
b1001 (
b1001 )
#100
0'
0&
0%
0$
0"
0!
b1010 (
b1010 )
