binary_to_gray/binary_to_gray.v
module binary_to_gray(bin,gray);
 input[3:0] bin;
 output[3:0]gray;
 assign gray[3]=bin[3];
 assign gray[2]=bin[3]^bin[2];
 assign gray[1]=bin[2]^bin[1];
 assign gray[0]=bin[1]^bin[0];
endmodule

binary_to_gray/binary_to_gray_tb.v
`include "binary_to_gray.v"
module binary_to_gray_tb();
reg [3:0] bin;
wire [3:0] gray;
binary_to_gray uut (bin,gray);
initial begin
    $dumpfile("binary_to_gray.vcd");
    $dumpvars(0,binary_to_gray_tb);
 bin=4'b0000; #10
 bin=4'b0001; #10
 bin=4'b0010; #10
 bin=4'b0011; #10
 bin=4'b0100; #10
 bin=4'b0101; #10
 bin=4'b0110; #10
 bin=4'b0111; #10
 bin=4'b1000; #10
 bin=4'b1001; #10
 bin=4'b1010; #10
 bin=4'b1011; #10
 bin=4'b1100; #10
 bin=4'b1101; #10
 bin=4'b1110; #10
 bin=4'b1111; #10

 $finish;
 end
endmodule

binary_to_gray/binary_to_gray.vcd
$date
	Wed Jun 11 19:15:45 2025
$end
$version
	Icarus Verilog
$end
$timescale
	1s
$end
$scope module binary_to_gray_tb $end
$var wire 4 ! gray [3:0] $end
$var reg 4 " bin [3:0] $end
$scope module uut $end
$var wire 4 # bin [3:0] $end
$var wire 4 $ gray [3:0] $end
$upscope $end
$upscope $end
$enddefinitions $end
$comment Show the parameter values. $end
$dumpall
$end
#0
$dumpvars
b0 $
b0 #
b0 "
b0 !
$end
#10
b1 !
b1 $
b1 "
b1 #
#20
b11 !
b11 $
b10 "
b10 #
#30
b10 !
b10 $
b11 "
b11 #
#40
b110 !
b110 $
b100 "
b100 #
#50
b111 !
b111 $
b101 "
b101 #
#60
b101 !
b101 $
b110 "
b110 #
#70
b100 !
b100 $
b111 "
b111 #
#80
b1100 !
b1100 $
b1000 "
b1000 #
#90
b1101 !
b1101 $
b1001 "
b1001 #
#100
b1111 !
b1111 $
b1010 "
b1010 #
#110
b1110 !
b1110 $
b1011 "
b1011 #
#120
b1010 !
b1010 $
b1100 "
b1100 #
#130
b1011 !
b1011 $
b1101 "
b1101 #
#140
b1001 !
b1001 $
b1110 "
b1110 #
#150
b1000 !
b1000 $
b1111 "
b1111 #
