full_subtractor/full_subtractor.v
module full_subtractor (difference,borrow,a,b,cin);
input a,b,cin;
output difference,borrow;
assign difference = a ^ b ^ cin;
assign borrow = ((~a)&b) | (b&cin) | ((~a)&cin);
endmodule

full_subtractor/full_subtractor_tb.v
`include "full_subtractor.v"
module full_subtractor_tb();
reg a,b,cin;
wire difference,borrow;
full_subtractor uut(difference,borrow,a,b,cin);
initial begin
    $dumpfile("full_subtractor.vcd");
    $dumpvars(0,full_subtractor_tb);

    a = 0; b = 0; cin = 0; #10
    a = 0; b = 0; cin = 1; #10
    a = 0; b = 1; cin = 0; #10
    a = 0; b = 1; cin = 1; #10
    a = 1; b = 0; cin = 0; #10
    a = 1; b = 0; cin = 1; #10
    a = 1; b = 1; cin = 0; #10
    a = 1; b = 1; cin = 1; #10

    $finish;
end
endmodule

full_subtractor/full_subtractor.vcd
$date
	Tue Jun 10 23:15:26 2025
$end
$version
	Icarus Verilog
$end
$timescale
	1s
$end
$scope module full_subtractor_tb $end
$var wire 1 ! difference $end
$var wire 1 " borrow $end
$var reg 1 # a $end
$var reg 1 $ b $end
$var reg 1 % cin $end
$scope module uut $end
$var wire 1 # a $end
$var wire 1 $ b $end
$var wire 1 " borrow $end
$var wire 1 % cin $end
$var wire 1 ! difference $end
$upscope $end
$upscope $end
$enddefinitions $end
$comment Show the parameter values. $end
$dumpall
$end
#0
$dumpvars
0%
0$
0#
0"
0!
$end
#10
1"
1!
1%
#20
0%
1$
#30
0!
1%
#40
0"
1!
0%
0$
1#
#50
0!
1%
#60
0%
1$
#70
1"
1!
1%
