encoder8_3/encoder8_3.v
 module encoder8_3(in,out);
 input[7:0] in;
 output reg[2:0] out;
 always @(*)
 begin
 out=3'b000;
 case(in)
 8'b00000000: out=3'b000;
 8'b00000001: out=3'b000;
 8'b00000010: out=3'b001;
 8'b00000100: out=3'b010;
 8'b00001000: out=3'b011;
 8'b00010000: out=3'b100;
 8'b00100000: out=3'b101;
 8'b01000000: out=3'b110;
 8'b10000000: out=3'b111;
 default: out=3'b000;
 endcase
 end
 endmodule

encoder8_3/encoder8_3_tb.v
`include "encoder8_3.v"
module encoder8_3_tb();
 reg [7:0]in;
 wire [2:0] out;
 encoder8_3 uut(in,out);
 initial
 begin
    $dumpfile("encoder8_3.vcd");
    $dumpvars(0,encoder8_3_tb);
 in=8'b00000001; #10
 in=8'b00000010; #10
 in=8'b00000100; #10
 in=8'b00001000; #10
 in=8'b00010000; #10
 in=8'b00100000; #10
 in=8'b01000000; #10
 in=8'b10000000; #10
 $finish;
 end
endmodule

encoder8_3/encoder8_3.vcd
$date
	Wed Jun 11 11:26:52 2025
$end
$version
	Icarus Verilog
$end
$timescale
	1s
$end
$scope module encoder8_3_tb $end
$var wire 3 ! out [2:0] $end
$var reg 8 " in [7:0] $end
$scope module uut $end
$var wire 8 # in [7:0] $end
$var reg 3 $ out [2:0] $end
$upscope $end
$upscope $end
$enddefinitions $end
$comment Show the parameter values. $end
$dumpall
$end
#0
$dumpvars
b0 $
b1 #
b1 "
b0 !
$end
#10
b1 !
b1 $
b10 "
b10 #
#20
b10 !
b10 $
b100 "
b100 #
#30
b11 !
b11 $
b1000 "
b1000 #
#40
b100 !
b100 $
b10000 "
b10000 #
#50
b101 !
b101 $
b100000 "
b100000 #
#60
b110 !
b110 $
b1000000 "
b1000000 #
#70
b111 !
b111 $
b10000000 "
b10000000 #
