gray_to_binary/gray_to_binary.v
 module gray_to_binary(gray,bin);
 input[3:0] gray;
 output[3:0] bin;
 assign bin[3]= gray[3];
 assign bin[2]=gray[2]^bin[3];
 assign bin[1]=gray[1]^bin[2];
 assign bin[0]=gray[0]^bin[1];
 endmodule

gray_to_binary/gray_to_binary_tb.v
`include "gray_to_binary.v"
module gray_to_binary_tb();
reg [3:0] gray;
wire [3:0] bin;
gray_to_binary uut (gray,bin);
initial begin
    $dumpfile("gray_to_binary.vcd");
    $dumpvars(0,gray_to_binary_tb);
    gray = 4'b0000; #10;
    gray = 4'b0001; #10;
    gray = 4'b0011; #10;
    gray = 4'b0110; #10;
    gray = 4'b0111; #10;
    gray = 4'b0101; #10;
    gray = 4'b0100; #10;
    gray = 4'b1100; #10;
    gray = 4'b1101; #10;
    gray = 4'b1111; #10;
    gray = 4'b1110; #10;
    gray = 4'b1010; #10;
    gray = 4'b1011; #10;
    gray = 4'b1001; #10;
    gray = 4'b1000; #10;

    $finish;
end
endmodule

gray_to_binary/gray_to_binary.vcd
$date
	Wed Jun 11 19:33:41 2025
$end
$version
	Icarus Verilog
$end
$timescale
	1s
$end
$scope module gray_to_binary_tb $end
$var wire 4 ! bin [3:0] $end
$var reg 4 " gray [3:0] $end
$scope module uut $end
$var wire 4 # gray [3:0] $end
$var wire 4 $ bin [3:0] $end
$upscope $end
$upscope $end
$enddefinitions $end
$comment Show the parameter values. $end
$dumpall
$end
#0
$dumpvars
b0 $
b0 #
b0 "
b0 !
$end
#10
b1 !
b1 $
b1 "
b1 #
#20
b10 !
b10 $
b11 "
b11 #
#30
b100 !
b100 $
b110 "
b110 #
#40
b101 !
b101 $
b111 "
b111 #
#50
b110 !
b110 $
b101 "
b101 #
#60
b111 !
b111 $
b100 "
b100 #
#70
b1000 !
b1000 $
b1100 "
b1100 #
#80
b1001 !
b1001 $
b1101 "
b1101 #
#90
b1010 !
b1010 $
b1111 "
b1111 #
#100
b1011 !
b1011 $
b1110 "
b1110 #
#110
b1100 !
b1100 $
b1010 "
b1010 #
#120
b1101 !
b1101 $
b1011 "
b1011 #
#130
b1110 !
b1110 $
b1001 "
b1001 #
#140
b1111 !
b1111 $
b1000 "
b1000 #
