even_parity_generator/even_parity_generator.v
 module even_parity_generator(in,p);
 input [3:0]in;
 output p;
 assign p=in[3]^in[2]^in[1]^in[0]; //sets the parity bit high if odd number of input bits is high.
 endmodule

even_parity_generator/even_parity_generator_tb.v
`include "even_parity_generator.v"
module even_parity_generator_tb();
reg [3:0]in;
wire p;
even_parity_generator uut (in,p);
initial begin
    $dumpfile("even_parity_generator.vcd");
    $dumpvars(0,even_parity_generator_tb);
 in=4'b0000; #10
 in=4'b0001; #10
 in=4'b0010; #10
 in=4'b0011; #10
 in=4'b0100; #10
 in=4'b0101; #10
 in=4'b0110; #10
 in=4'b0111; #10
 in=4'b1000; #10
 in=4'b1001; #10
 in=4'b1010; #10
 in=4'b1011; #10
 in=4'b1100; #10
 in=4'b1101; #10
 in=4'b1110; #10
 in=4'b1111; #10
 $finish;
 end
endmodule

even_parity_generator/even_parity_generator.vcd
$date
	Thu Jun 12 23:06:56 2025
$end
$version
	Icarus Verilog
$end
$timescale
	1s
$end
$scope module even_parity_generator_tb $end
$var wire 1 ! p $end
$var reg 4 " in [3:0] $end
$scope module uut $end
$var wire 4 # in [3:0] $end
$var wire 1 ! p $end
$upscope $end
$upscope $end
$enddefinitions $end
$comment Show the parameter values. $end
$dumpall
$end
#0
$dumpvars
b0 #
b0 "
0!
$end
#10
1!
b1 "
b1 #
#20
1!
b10 "
b10 #
#30
0!
b11 "
b11 #
#40
1!
b100 "
b100 #
#50
0!
b101 "
b101 #
#60
0!
b110 "
b110 #
#70
1!
b111 "
b111 #
#80
1!
b1000 "
b1000 #
#90
0!
b1001 "
b1001 #
#100
0!
b1010 "
b1010 #
#110
1!
b1011 "
b1011 #
#120
0!
b1100 "
b1100 #
#130
1!
b1101 "
b1101 #
#140
1!
b1110 "
b1110 #
#150
0!
b1111 "
b1111 #
