demux1_8/demux1_8.v
module demux1_8(out,sel,in);
input [2:0]sel;
input in;
output reg [7:0] out;
always @(*)begin
    out = 8'b00000000;
    case(sel)
    3'b000 : out[0] = in;
    3'b001 : out[1] = in;
    3'b010 : out[2] = in;
    3'b011 : out[3] = in;
    3'b100 : out[4] = in;
    3'b101 : out[5] = in;
    3'b110 : out[6] = in;
    3'b111 : out[7] = in;
default:out=8'b00000000;
    endcase
end
endmodule

demux1_8/demux1_8_tb.v
`include "demux1_8.v"
module demux1_8_tb();
reg [2:0]sel;
reg in;
wire [7:0]out;
demux1_8 uut(out,sel,in);
initial begin
    $dumpfile("demux1_8.vcd");
    $dumpvars(0,demux1_8_tb);
    in = 1;
    sel = 3'b000; #10
    sel = 3'b001; #10
    sel = 3'b010; #10
    sel = 3'b011; #10
    sel = 3'b100; #10
    sel = 3'b101; #10
    sel = 3'b110; #10
    sel = 3'b111; #10
    in = 0; sel = 3'b101; #10
    $finish;
end
endmodule

demux1_8/demux1_8.vcd
$date
	Wed Jun 11 11:08:26 2025
$end
$version
	Icarus Verilog
$end
$timescale
	1s
$end
$scope module demux1_8_tb $end
$var wire 8 ! out [7:0] $end
$var reg 1 " in $end
$var reg 3 # sel [2:0] $end
$scope module uut $end
$var wire 1 " in $end
$var wire 3 $ sel [2:0] $end
$var reg 8 % out [7:0] $end
$upscope $end
$upscope $end
$enddefinitions $end
$comment Show the parameter values. $end
$dumpall
$end
#0
$dumpvars
b1 %
b0 $
b0 #
1"
b1 !
$end
#10
b10 !
b10 %
b1 #
b1 $
#20
b100 !
b100 %
b10 #
b10 $
#30
b1000 !
b1000 %
b11 #
b11 $
#40
b10000 !
b10000 %
b100 #
b100 $
#50
b100000 !
b100000 %
b101 #
b101 $
#60
b1000000 !
b1000000 %
b110 #
b110 $
#70
b10000000 !
b10000000 %
b111 #
b111 $
#80
b0 !
b0 %
b101 #
b101 $
0"
