mux8_1/mux8_1.v
module mux8_1 (out,sel,in);
input [2:0] sel;
input [7:0]in;
output reg out;
always @(*)
 begin 
case(sel)
 3'b000: out=in[0];
 3'b001: out=in[1];
 3'b010: out=in[2];
 3'b011: out=in[3];
 3'b100: out=in[4];
 3'b101: out=in[5];
 3'b110: out=in[6];
 3'b111: out=in[7];
 default: out=0;
 endcase
 end
endmodule

mux8_1/mux8_1_tb.v
`include "mux8_1.v"
module mux8_1_tb();
reg [2:0]sel;
reg [7:0]in;
wire out;
mux8_1 uut(out,sel,in);
initial begin
    $dumpfile("mux8_1.vcd");
    $dumpvars(0,mux8_1_tb);
    in=8'b10101010;
 sel=3'b000; #10
 sel=3'b001; #10
 sel=3'b010; #10
 sel=3'b011; #10
 sel=3'b100; #10
 sel=3'b101; #10
 sel=3'b110; #10
 sel=3'b111; #10
 in=8'b11110000; 
 sel=3'b000; #10
 sel=3'b001; #10
 sel=3'b010; #10
 sel=3'b011; #10
 sel=3'b100; #10
 sel=3'b101; #10
 sel=3'b110; #10
 sel=3'b111; #10
 $finish;
 end
 endmodule

mux8_1/mux8_1.vcd
$date
	Wed Jun 11 02:53:23 2025
$end
$version
	Icarus Verilog
$end
$timescale
	1s
$end
$scope module mux8_1_tb $end
$var wire 1 ! out $end
$var reg 8 " in [7:0] $end
$var reg 3 # sel [2:0] $end
$scope module uut $end
$var wire 8 $ in [7:0] $end
$var wire 3 % sel [2:0] $end
$var reg 1 ! out $end
$upscope $end
$upscope $end
$enddefinitions $end
$comment Show the parameter values. $end
$dumpall
$end
#0
$dumpvars
b0 %
b10101010 $
b0 #
b10101010 "
0!
$end
#10
1!
b1 #
b1 %
#20
0!
b10 #
b10 %
#30
1!
b11 #
b11 %
#40
0!
b100 #
b100 %
#50
1!
b101 #
b101 %
#60
0!
b110 #
b110 %
#70
1!
b111 #
b111 %
#80
0!
b0 #
b0 %
b11110000 "
b11110000 $
#90
b1 #
b1 %
#100
b10 #
b10 %
#110
b11 #
b11 %
#120
1!
b100 #
b100 %
#130
b101 #
b101 %
#140
b110 #
b110 %
#150
b111 #
b111 %
