full_subtractor_using_half_subtractor/full_subtractor_hs.v
module half_subtractor(difference,borrow,a,b);
input a,b;
output difference,borrow;
assign difference = a ^ b;
assign borrow = (~a) & b;
endmodule

module full_subtractor_hs(difference,borrow,a,b,cin);
input a,b,cin;
output difference,borrow;
wire partial_difference,partial_borrow,borrow1;
half_subtractor h1 (partial_difference,partial_borrow,a,b);
half_subtractor h2 (difference,borrow1,partial_difference,cin);
assign borrow = partial_borrow | borrow1;
endmodule

full_subtractor_using_half_subtractor/full_subtractor_hs_tb.v
`include "full_subtractor_hs.v"
module full_subtractor_hs_tb();
reg a,b,cin;
wire difference,borrow;
full_subtractor_hs uut(difference,borrow,a,b,cin);
initial begin
    $dumpfile("full_subtractor_hs.vcd");
    $dumpvars(0,full_subtractor_hs_tb);

    a = 0; b = 0; cin = 0; #10
    a = 0; b = 0; cin = 1; #10
    a = 0; b = 1; cin = 0; #10
    a = 0; b = 1; cin = 1; #10
    a = 1; b = 0; cin = 0; #10
    a = 1; b = 0; cin = 1; #10
    a = 1; b = 1; cin = 0; #10
    a = 1; b = 1; cin = 1; #10

    $finish;
end
endmodule

full_subtractor_using_half_subtractor/full_subtractor_hs.vcd
$date
	Tue Jun 10 23:38:14 2025
$end
$version
	Icarus Verilog
$end
$timescale
	1s
$end
$scope module full_subtractor_hs_tb $end
$var wire 1 ! difference $end
$var wire 1 " borrow $end
$var reg 1 # a $end
$var reg 1 $ b $end
$var reg 1 % cin $end
$scope module uut $end
$var wire 1 # a $end
$var wire 1 $ b $end
$var wire 1 " borrow $end
$var wire 1 % cin $end
$var wire 1 & partial_difference $end
$var wire 1 ' partial_borrow $end
$var wire 1 ! difference $end
$var wire 1 ( borrow1 $end
$scope module h1 $end
$var wire 1 # a $end
$var wire 1 $ b $end
$var wire 1 ' borrow $end
$var wire 1 & difference $end
$upscope $end
$scope module h2 $end
$var wire 1 & a $end
$var wire 1 % b $end
$var wire 1 ( borrow $end
$var wire 1 ! difference $end
$upscope $end
$upscope $end
$upscope $end
$enddefinitions $end
$comment Show the parameter values. $end
$dumpall
$end
#0
$dumpvars
0(
0'
0&
0%
0$
0#
0"
0!
$end
#10
1"
1!
1(
1%
#20
0(
1&
1'
0%
1$
#30
0!
1%
#40
0"
1!
0'
0%
0$
1#
#50
0!
1%
#60
0&
0%
1$
#70
1"
1!
1(
1%
