full_adder_using_half_adder/full_adder_hf.v
module half_adder(sum,carry,in1,in2);
input in1,in2;
output sum,carry;
assign sum = in1 ^ in2;
assign carry = in1 & in2;
endmodule

module full_adder_hf(sum,carry,a,b,cin);
input a,b,cin;
output sum,carry;
wire partial_sum,partial_carry,carry1;
half_adder h1 (partial_sum,partial_carry,a,b);
half_adder h2 (sum,carry1,partial_sum,cin);
assign carry = partial_carry | carry1;
endmodule

full_adder_using_half_adder/full_adder_hf_tb.v
`include "full_adder_hf.v"
module full_adder_hf_tb();
reg a,b,cin;
wire sum,carry;
full_adder_hf uut(sum,carry,a,b,cin);
initial begin
    $dumpfile("full_adder_hf.vcd");
    $dumpvars(0,full_adder_hf_tb);

    a = 0; b = 0; cin = 0; #10
    a = 0; b = 0; cin = 1; #10
    a = 0; b = 1; cin = 0; #10
    a = 0; b = 1; cin = 1; #10
    a = 1; b = 0; cin = 0; #10
    a = 1; b = 0; cin = 1; #10
    a = 1; b = 1; cin = 0; #10
    a = 1; b = 1; cin = 1; #10

    $finish;
end
endmodule

full_adder_using_half_adder/full_adder_hf.vcd
$date
	Tue Jun 10 22:11:32 2025
$end
$version
	Icarus Verilog
$end
$timescale
	1s
$end
$scope module full_adder_hf_tb $end
$var wire 1 ! sum $end
$var wire 1 " carry $end
$var reg 1 # a $end
$var reg 1 $ b $end
$var reg 1 % cin $end
$scope module uut $end
$var wire 1 # a $end
$var wire 1 $ b $end
$var wire 1 " carry $end
$var wire 1 % cin $end
$var wire 1 ! sum $end
$var wire 1 & partial_sum $end
$var wire 1 ' partial_carry $end
$var wire 1 ( carry1 $end
$scope module h1 $end
$var wire 1 ' carry $end
$var wire 1 # in1 $end
$var wire 1 $ in2 $end
$var wire 1 & sum $end
$upscope $end
$scope module h2 $end
$var wire 1 ( carry $end
$var wire 1 & in1 $end
$var wire 1 % in2 $end
$var wire 1 ! sum $end
$upscope $end
$upscope $end
$upscope $end
$enddefinitions $end
$comment Show the parameter values. $end
$dumpall
$end
#0
$dumpvars
0(
0'
0&
0%
0$
0#
0"
0!
$end
#10
1!
1%
#20
1&
0%
1$
#30
1"
0!
1(
1%
#40
0"
1!
0(
0%
0$
1#
#50
1"
0!
1(
1%
#60
0(
0&
1'
0%
1$
#70
1!
1%
