odd_parity_checker/odd_parity_checker.v
module odd_parity_checker(in,p,error);
 input[3:0]in;
 input p;
 output error;
 assign error=~(in[3]^in[2]^in[1]^in[0])^p;
 endmodule

odd_parity_checker/odd_parity_checker_tb.v
`include "odd_parity_checker.v"
module odd_parity_checker_tb();
reg [3:0]in;
reg p;
wire error;
odd_parity_checker uut (in,p,error);
initial begin
    $dumpfile("odd_parity_checker.vcd");
    $dumpvars(0,odd_parity_checker_tb);
 in=4'b0000;p=1'b0; #10
 in=4'b0001;p=1'b1; #10
 in=4'b0010;p=1'b0; #10
 in=4'b0011;p=1'b1; #10
 in=4'b0100;p=1'b0; #10
 in=4'b0101;p=1'b1; #10
 in=4'b0110;p=1'b0; #10
 in=4'b0111;p=1'b1; #10
 in=4'b1000;p=1'b0; #10
 in=4'b1001;p=1'b1; #10
 in=4'b1010;p=1'b0; #10
 in=4'b1011;p=1'b1; #10
 in=4'b1100;p=1'b0; #10
 in=4'b1101;p=1'b1; #10
 in=4'b1110;p=1'b0; #10
 in=4'b1111;p=1'b1; #10
 $finish;
 end
endmodule

odd_parity_checker/odd_parity_checker.vcd
$date
	Fri Jun 13 00:31:50 2025
$end
$version
	Icarus Verilog
$end
$timescale
	1s
$end
$scope module odd_parity_checker_tb $end
$var wire 1 ! error $end
$var reg 4 " in [3:0] $end
$var reg 1 # p $end
$scope module uut $end
$var wire 1 ! error $end
$var wire 4 $ in [3:0] $end
$var wire 1 # p $end
$upscope $end
$upscope $end
$enddefinitions $end
$comment Show the parameter values. $end
$dumpall
$end
#0
$dumpvars
b0 $
0#
b0 "
1!
$end
#10
1!
1#
b1 "
b1 $
#20
0!
0#
b10 "
b10 $
#30
0!
1#
b11 "
b11 $
#40
0!
0#
b100 "
b100 $
#50
0!
1#
b101 "
b101 $
#60
1!
0#
b110 "
b110 $
#70
1!
1#
b111 "
b111 $
#80
0!
0#
b1000 "
b1000 $
#90
0!
1#
b1001 "
b1001 $
#100
1!
0#
b1010 "
b1010 $
#110
1!
1#
b1011 "
b1011 $
#120
1!
0#
b1100 "
b1100 $
#130
1!
1#
b1101 "
b1101 $
#140
0!
0#
b1110 "
b1110 $
#150
0!
1#
b1111 "
b1111 $
