mux8_1_using_2_1/mux8_1_2_1.v
module mux2_1(out,sel,a,b);
input sel,a,b;
output out;
assign out = sel ? b : a;
endmodule

module mux8_1_2_1(out,sel,in);
input [2:0]sel;
input [7:0]in;
output out;
wire [5:0]w;

mux2_1 m1(w[0],sel[0],in[0],in[1]);
mux2_1 m2(w[1],sel[0],in[2],in[3]);
mux2_1 m3(w[2],sel[0],in[4],in[5]);
mux2_1 m4(w[3],sel[0],in[6],in[7]);

mux2_1 m5(w[4],sel[1],w[0],w[1]);
mux2_1 m6(w[5],sel[1],w[2],w[3]);

mux2_1 m7(out,sel[2],w[4],w[5]);
endmodule

mux8_1_using_2_1/mux8_1_2_1_tb.v
`include "mux8_1_2_1.v"
module mux8_1_2_1_tb();
reg [2:0]sel;
reg [7:0]in;
wire out;
mux8_1_2_1 uut(out,sel,in);
initial begin
    $dumpfile("mux8_1_2_1.vcd");
    $dumpvars(0,mux8_1_2_1_tb);
    in=8'b10101010;
 sel=3'b000; #10
 sel=3'b001; #10
 sel=3'b010; #10
 sel=3'b011; #10
 sel=3'b100; #10
 sel=3'b101; #10
 sel=3'b110; #10
 sel=3'b111; #10
 in=8'b11110000; 
 sel=3'b000; #10
 sel=3'b001; #10
 sel=3'b010; #10
 sel=3'b011; #10
 sel=3'b100; #10
 sel=3'b101; #10
 sel=3'b110; #10
 sel=3'b111; #10
 $finish;
 end
 endmodule

mux8_1_using_2_1/mux8_1_2_1.vcd
$date
	Wed Jun 11 09:57:32 2025
$end
$version
	Icarus Verilog
$end
$timescale
	1s
$end
$scope module mux8_1_2_1_tb $end
$var wire 1 ! out $end
$var reg 8 " in [7:0] $end
$var reg 3 # sel [2:0] $end
$scope module uut $end
$var wire 8 $ in [7:0] $end
$var wire 3 % sel [2:0] $end
$var wire 6 & w [5:0] $end
$var wire 1 ! out $end
$scope module m1 $end
$var wire 1 ' a $end
$var wire 1 ( b $end
$var wire 1 ) sel $end
$var wire 1 * out $end
$upscope $end
$scope module m2 $end
$var wire 1 + a $end
$var wire 1 , b $end
$var wire 1 - sel $end
$var wire 1 . out $end
$upscope $end
$scope module m3 $end
$var wire 1 / a $end
$var wire 1 0 b $end
$var wire 1 1 sel $end
$var wire 1 2 out $end
$upscope $end
$scope module m4 $end
$var wire 1 3 a $end
$var wire 1 4 b $end
$var wire 1 5 sel $end
$var wire 1 6 out $end
$upscope $end
$scope module m5 $end
$var wire 1 7 a $end
$var wire 1 8 b $end
$var wire 1 9 sel $end
$var wire 1 : out $end
$upscope $end
$scope module m6 $end
$var wire 1 ; a $end
$var wire 1 < b $end
$var wire 1 = sel $end
$var wire 1 > out $end
$upscope $end
$scope module m7 $end
$var wire 1 ? a $end
$var wire 1 @ b $end
$var wire 1 A sel $end
$var wire 1 ! out $end
$upscope $end
$upscope $end
$upscope $end
$enddefinitions $end
$comment Show the parameter values. $end
$dumpall
$end
#0
$dumpvars
0A
0@
0?
0>
0=
0<
0;
0:
09
08
07
06
05
14
03
02
01
10
0/
0.
0-
1,
0+
0*
0)
1(
0'
b0 &
b0 %
b10101010 $
b0 #
b10101010 "
0!
$end
#10
1!
1?
1@
1:
1>
17
18
1;
1<
1*
1.
12
b111111 &
16
1)
1-
11
15
b1 #
b1 %
#20
0!
0?
0@
0:
0>
07
08
0;
0<
0*
0.
02
b0 &
06
0)
0-
01
05
19
1=
b10 #
b10 %
#30
1!
1?
1@
1:
1>
17
18
1;
1<
1*
1.
12
b111111 &
16
1)
1-
11
15
b11 #
b11 %
#40
0!
0?
0@
0:
0>
07
08
0;
0<
0*
0.
02
b0 &
06
0)
0-
01
05
09
0=
1A
b100 #
b100 %
#50
1!
1?
1@
1:
1>
17
18
1;
1<
1*
1.
12
b111111 &
16
1)
1-
11
15
b101 #
b101 %
#60
0!
0?
0@
0:
0>
07
08
0;
0<
0*
0.
02
b0 &
06
0)
0-
01
05
19
1=
b110 #
b110 %
#70
1!
1?
1@
1:
1>
17
18
1;
1<
1*
1.
12
b111111 &
16
1)
1-
11
15
b111 #
b111 %
#80
0!
0?
0:
07
08
0*
b101100 &
0.
0)
0-
01
05
09
0=
0A
0(
0,
1/
13
b0 #
b0 %
b11110000 "
b11110000 $
#90
1)
1-
11
15
b1 #
b1 %
#100
0)
0-
01
05
19
1=
b10 #
b10 %
#110
1)
1-
11
15
b11 #
b11 %
#120
1!
0)
0-
01
05
09
0=
1A
b100 #
b100 %
#130
1)
1-
11
15
b101 #
b101 %
#140
0)
0-
01
05
19
1=
b110 #
b110 %
#150
1)
1-
11
15
b111 #
b111 %
