odd_parity_generator/odd_parity_generator.v
 module odd_parity_generator(in,p);
 input [3:0]in;
 output p;
 assign p= ~(in[3]^in[2]^in[1]^in[0]); //sets the parity bit high if even number of input bits is high.
 endmodule

odd_parity_generator/odd_parity_generator_tb.v
`include "odd_parity_generator.v"
module odd_parity_generator_tb();
reg [3:0]in;
wire p;
odd_parity_generator uut (in,p);
initial begin
    $dumpfile("odd_parity_generator.vcd");
    $dumpvars(0,odd_parity_generator_tb);
 in=4'b0000; #10
 in=4'b0001; #10
 in=4'b0010; #10
 in=4'b0011; #10
 in=4'b0100; #10
 in=4'b0101; #10
 in=4'b0110; #10
 in=4'b0111; #10
 in=4'b1000; #10
 in=4'b1001; #10
 in=4'b1010; #10
 in=4'b1011; #10
 in=4'b1100; #10
 in=4'b1101; #10
 in=4'b1110; #10
 in=4'b1111; #10
 $finish;
 end
endmodule

odd_parity_generator/odd_parity_generator.vcd
$date
	Thu Jun 12 23:18:44 2025
$end
$version
	Icarus Verilog
$end
$timescale
	1s
$end
$scope module odd_parity_generator_tb $end
$var wire 1 ! p $end
$var reg 4 " in [3:0] $end
$scope module uut $end
$var wire 4 # in [3:0] $end
$var wire 1 ! p $end
$upscope $end
$upscope $end
$enddefinitions $end
$comment Show the parameter values. $end
$dumpall
$end
#0
$dumpvars
b0 #
b0 "
1!
$end
#10
0!
b1 "
b1 #
#20
0!
b10 "
b10 #
#30
1!
b11 "
b11 #
#40
0!
b100 "
b100 #
#50
1!
b101 "
b101 #
#60
1!
b110 "
b110 #
#70
0!
b111 "
b111 #
#80
0!
b1000 "
b1000 #
#90
1!
b1001 "
b1001 #
#100
1!
b1010 "
b1010 #
#110
0!
b1011 "
b1011 #
#120
1!
b1100 "
b1100 #
#130
0!
b1101 "
b1101 #
#140
0!
b1110 "
b1110 #
#150
1!
b1111 "
b1111 #
